dkist_service_configuration/__init__.py
dkist_service_configuration/_version.py
dkist_service_configuration/logging.py
dkist_service_configuration/message_processor.py
dkist_service_configuration/middleware.py
dkist_service_configuration/retryer.py
dkist_service_configuration/settings.py
dkist_service_configuration/tests/__init__.py
dkist_service_configuration/tests/conftest.py
dkist_service_configuration/tests/test_logging.py
dkist_service_configuration/tests/test_message_processor.py
dkist_service_configuration/tests/test_middleware.py
dkist_service_configuration/tests/test_retryer.py
dkist_service_configuration/tests/test_settings.py
dkist_service_configuration-4.1.12.dist-info/licenses/LICENSE
dkist_service_configuration-4.1.12.dist-info/METADATA
dkist_service_configuration-4.1.12.dist-info/WHEEL
dkist_service_configuration-4.1.12.dist-info/top_level.txt
dkist_service_configuration-4.1.12.dist-info/RECORD
