Metadata-Version: 2.4
Name: dkist-service-configuration
Version: 4.1.12
Summary: Library for retrieving configurations for DKIST services
Author-email: NSO / AURA <dkistdc@nso.edu>
License: BSD 3-Clause
Project-URL: repository, https://bitbucket.org/dkistdc/dkist_service_configuration
Classifier: License :: OSI Approved :: MIT License
Classifier: Programming Language :: Python :: 3
Classifier: Programming Language :: Python :: 3.11
Requires-Python: >=3.11
License-File: LICENSE
Requires-Dist: loguru~=0.7.0
Requires-Dist: pydantic-settings~=2.0
Requires-Dist: pydantic~=2.0
Requires-Dist: tenacity<10.0,>=8.2
Requires-Dist: opentelemetry-sdk~=1.31
Requires-Dist: opentelemetry-exporter-otlp~=1.31
Requires-Dist: opentelemetry-instrumentation-pika~=0.52b0
Requires-Dist: opentelemetry-instrumentation-system-metrics[instruments]~=0.52b0
Requires-Dist: opentelemetry-instrumentation-requests~=0.52b0
Requires-Dist: opentelemetry-instrumentation-aiohttp-client~=0.52b0
Requires-Dist: opentelemetry-instrumentation-botocore~=0.52b0
Requires-Dist: opentelemetry-instrumentation-celery~=0.52b0
Requires-Dist: opentelemetry-instrumentation-fastapi~=0.52b0
Requires-Dist: opentelemetry-instrumentation-psycopg2~=0.52b0
Requires-Dist: opentelemetry-instrumentation-pymongo~=0.52b0
Requires-Dist: opentelemetry-instrumentation-redis~=0.52b0
Requires-Dist: opentelemetry-instrumentation-sqlalchemy~=0.52b0
Provides-Extra: test
Requires-Dist: tox>=4; extra == "test"
Requires-Dist: pytest; extra == "test"
Requires-Dist: pytest-cov; extra == "test"
Requires-Dist: talus~=1.3; extra == "test"
Requires-Dist: fastapi[all]~=0.116.1; extra == "test"
Requires-Dist: secure~=1.0.1; extra == "test"
Provides-Extra: isb
Requires-Dist: talus~=1.3; extra == "isb"
Provides-Extra: fastapi
Requires-Dist: fastapi~=0.116.1; extra == "fastapi"
Requires-Dist: secure~=1.0.1; extra == "fastapi"
Dynamic: license-file
